environment_helpers/__init__.py
environment_helpers/build.py
environment_helpers/install.py
environment_helpers/introspect.py
environment_helpers/_scripts/call.py
environment_helpers/_scripts/launcher-kind.py
environment_helpers/_scripts/scheme.py
environment_helpers/_scripts/system-scheme.py
environment_helpers/_scripts/version.py
environment_helpers-0.3.0.dist-info/licenses/LICENSE
environment_helpers-0.3.0.dist-info/WHEEL
environment_helpers-0.3.0.dist-info/METADATA
environment_helpers-0.3.0.dist-info/RECORD
