Metadata-Version: 2.4
Name: environment-helpers
Version: 0.3.0
Summary: Collection of helpers for managing Python environments
Author-email: Filipe Laíns <lains@riseup.net>
Requires-Python: >= 3.10
Classifier: License :: OSI Approved :: MIT License
Classifier: Programming Language :: Python :: 3
Classifier: Programming Language :: Python :: 3 :: Only
Classifier: Programming Language :: Python :: 3.9
Classifier: Programming Language :: Python :: 3.10
Classifier: Programming Language :: Python :: 3.11
Classifier: Programming Language :: Python :: 3.12
Classifier: Programming Language :: Python :: 3.13
Classifier: Programming Language :: Python :: Implementation :: CPython
Classifier: Programming Language :: Python :: Implementation :: PyPy
License-File: LICENSE
Requires-Dist: build >= 0.5.0
Requires-Dist: installer >= 0.5.0
Requires-Dist: typing_extensions >= 4.3.0; python_version < "3.11"
Requires-Dist: furo >= 2023.08.17 ; extra == "docs"
Requires-Dist: sphinx ~= 7.0 ; extra == "docs"
Requires-Dist: sphinx-autodoc-typehints >= 1.10 ; extra == "docs"
Requires-Dist: pytest >= 7 ; extra == "test"
Requires-Dist: pytest-cov >= 5 ; extra == "test"
Requires-Dist: pytest-mock >= 2 ; extra == "test"
Requires-Dist: podman >= 5 ; extra == "test"
Project-URL: changelog, https://environment-helpers.readthedocs.io/en/stable/changelog.html
Project-URL: homepage, https://github.com/FFY00/environment-helpers
Provides-Extra: docs
Provides-Extra: test
